aldjemy/__init__.py
aldjemy/apps.py
aldjemy/core.py
aldjemy/meta.py
aldjemy/orm.py
aldjemy/sqlite.py
aldjemy/table.py
aldjemy/wrapper.py
aldjemy_cai-1.0.dist-info/LICENSE
aldjemy_cai-1.0.dist-info/METADATA
aldjemy_cai-1.0.dist-info/WHEEL
aldjemy_cai-1.0.dist-info/top_level.txt
aldjemy_cai-1.0.dist-info/RECORD
