Metadata-Version: 2.1
Name: aldjemy-cai
Version: 1.0
Summary: SQLAlchemy for your Django models
Home-page: https://github.com/character-tech/aldjemy
Requires-Python: >=3.6.1,<4.0
License-File: LICENSE
Requires-Dist: Django>=2.2
Requires-Dist: SQLAlchemy>=1.4
